giphyFun/__init__.py
giphyFun/giphyFun.py
giphyfun-0.2.dist-info/LICENSE
giphyfun-0.2.dist-info/METADATA
giphyfun-0.2.dist-info/WHEEL
giphyfun-0.2.dist-info/entry_points.txt
giphyfun-0.2.dist-info/top_level.txt
giphyfun-0.2.dist-info/RECORD
