Metadata-Version: 2.1
Name: giphyfun
Version: 0.2
Summary: Command line program that play random giphy.
Home-page: https://github.com/vsDeus/giphyFun
Author: Goia Ciprian
Author-email: goia.ciprian14@gamil.com
License: UNKNOWN
Download-URL: https://github.com/vsDeus/giphyFun/archive/0.1.tar.gz
Keywords: giphy,terminal,giphyfun
Platform: UNKNOWN
Classifier: Development Status :: 3 - Alpha
Classifier: Intended Audience :: Developers
Classifier: Topic :: Software Development :: Build Tools
Classifier: Programming Language :: Python :: 3
Classifier: Programming Language :: Python :: 3.6
Classifier: Programming Language :: Python :: 3.7
Requires-Dist: opencv-python
Requires-Dist: appdirs
Requires-Dist: clipboard
